{
  "vehicle": {
    "frame_no": "43284",
    "engine_no": "11204",
    "model_colour": "Spet Aro, RPB",
    "key_no": "1267",
    "battery_no": "3302419"
  },
  "customer": {
    "gender": "Male",
    "year_of_birth": "1975",
    "date_of_birth": "01/01/1975",
    "name": "Shivnarayan",
    "care_of": "S/O Phaguni",
    "state": "Rajasthan",
    "pin_code": "321408",
    "address": "S/O Phaguni, gaon azdapura, 49 ERHIGH. Gllda, HARR, Chak Dharsoni, Jeewad, Bharatpur, 321408 Rajasthan, 321408",
    "city": "Bharatpur",
    "mobile_number": "8279246146",
    "alt_phone_num": "9929182056",
    "aadhar_id": "7346"
  },
  "insurance": {
    "profession": "private",
    "insurer": "univarsal Sampoo",
    "marital_status": "Married",
    "nominee_gender": "Male",
    "nominee_name": "Ajay",
    "nominee_age": "21",
    "nominee_relationship": "Son",
    "financier": "Insurer Name (if needed):"
  },
  "details_customer_name": "Shivnarayan"
}